odoo9_addon_website_sale_stock_control-9.0.1.0.0-py2.7-nspkg.pth
odoo9_addon_website_sale_stock_control-9.0.1.0.0.dist-info/DESCRIPTION.rst
odoo9_addon_website_sale_stock_control-9.0.1.0.0.dist-info/METADATA
odoo9_addon_website_sale_stock_control-9.0.1.0.0.dist-info/RECORD
odoo9_addon_website_sale_stock_control-9.0.1.0.0.dist-info/WHEEL
odoo9_addon_website_sale_stock_control-9.0.1.0.0.dist-info/metadata.json
odoo9_addon_website_sale_stock_control-9.0.1.0.0.dist-info/namespace_packages.txt
odoo9_addon_website_sale_stock_control-9.0.1.0.0.dist-info/top_level.txt
odoo_addons/website_sale_stock_control/README.rst
odoo_addons/website_sale_stock_control/__init__.py
odoo_addons/website_sale_stock_control/__openerp__.py
odoo_addons/website_sale_stock_control/controllers/__init__.py
odoo_addons/website_sale_stock_control/controllers/main.py
odoo_addons/website_sale_stock_control/i18n/es.po
odoo_addons/website_sale_stock_control/models/__init__.py
odoo_addons/website_sale_stock_control/models/product.py
odoo_addons/website_sale_stock_control/static/description/icon.png
odoo_addons/website_sale_stock_control/static/src/css/website_sale_stock_control.less
odoo_addons/website_sale_stock_control/static/src/js/website_sale_stock_control.js
odoo_addons/website_sale_stock_control/static/src/xml/website_sale_stock_control_product_availability.xml
odoo_addons/website_sale_stock_control/tests/__init__.py
odoo_addons/website_sale_stock_control/tests/test_website_sale_stock_control.py
odoo_addons/website_sale_stock_control/views/assets.xml
odoo_addons/website_sale_stock_control/views/product_template_views.xml
odoo_addons/website_sale_stock_control/views/templates.xml
